jumbo/__init__.py
jumbo/config.py
jumbo/database.py
jumbo/handlers.py
jumbo/utils.py
jumbo-1.0.2.dist-info/COPYING
jumbo-1.0.2.dist-info/METADATA
jumbo-1.0.2.dist-info/WHEEL
jumbo-1.0.2.dist-info/top_level.txt
jumbo-1.0.2.dist-info/RECORD
