Metadata-Version: 2.1
Name: jumbo
Version: 1.0.2
Summary: A psycopg2 PostgreSQL wrapper for data science
Home-page: https://gitlab.com/amv213/jumbo
Author: Alvise Vianello
Author-email: alvise@vianello.ai
License: UNKNOWN
Platform: UNKNOWN
Classifier: Development Status :: 5 - Production/Stable
Classifier: Programming Language :: Python :: 3
Classifier: License :: OSI Approved :: GNU General Public License v3 or later (GPLv3+)
Classifier: Operating System :: OS Independent
Classifier: Topic :: Database
Classifier: Topic :: Scientific/Engineering
Classifier: Intended Audience :: End Users/Desktop
Classifier: Intended Audience :: Science/Research
Classifier: Intended Audience :: System Administrators
Requires-Python: >=3.8
Requires-Dist: eventlet
Requires-Dist: numpy
Requires-Dist: pandas
Requires-Dist: psycopg2
Requires-Dist: pygtail
Requires-Dist: python-dotenv
Requires-Dist: sqlalchemy
Requires-Dist: watchdog
Provides-Extra: doc
Requires-Dist: myst-parser ; extra == 'doc'
Requires-Dist: sphinx ; extra == 'doc'
Requires-Dist: sphinx-book-theme ; extra == 'doc'
Requires-Dist: sphinx-copybutton ; extra == 'doc'
Requires-Dist: sphinx-togglebutton ; extra == 'doc'
Requires-Dist: sphinx-panels ; extra == 'doc'
